_hydrogenlib_ctypes/__about__.py
_hydrogenlib_ctypes/__init__.py
_hydrogenlib_ctypes/_dll.py
_hydrogenlib_ctypes/_func.py
_hydrogenlib_ctypes/_special_methods.py
_hydrogenlib_ctypes/_special_methods.pyi
_hydrogenlib_ctypes/_types.py
hydrogenlib_ctypes-0.4.0.dist-info/METADATA
hydrogenlib_ctypes-0.4.0.dist-info/WHEEL
hydrogenlib_ctypes-0.4.0.dist-info/RECORD
